gnomad_toolbox/__init__.py
gnomad_toolbox/load_data.py
gnomad_toolbox/scripts.py
gnomad_toolbox/analysis/__init__.py
gnomad_toolbox/analysis/general.py
gnomad_toolbox/configs/jupyter_notebook_config.json
gnomad_toolbox/configs/lab/user-settings/@jupyterlab/toc-extension/plugin.jupyterlab-settings
gnomad_toolbox/configs/nbconfig/notebook.json
gnomad_toolbox/configs/nbconfig/tree.json
gnomad_toolbox/filtering/__init__.py
gnomad_toolbox/filtering/constraint.py
gnomad_toolbox/filtering/coverage.py
gnomad_toolbox/filtering/frequency.py
gnomad_toolbox/filtering/pext.py
gnomad_toolbox/filtering/variant.py
gnomad_toolbox/filtering/vep.py
gnomad_toolbox/notebooks/dive_into_secondary_analyses.ipynb
gnomad_toolbox/notebooks/explore_release_data.ipynb
gnomad_toolbox/notebooks/intro_to_filtering_variant_data.ipynb
gnomad_toolbox-0.0.1.dist-info/LICENSE
gnomad_toolbox-0.0.1.dist-info/METADATA
gnomad_toolbox-0.0.1.dist-info/WHEEL
gnomad_toolbox-0.0.1.dist-info/entry_points.txt
gnomad_toolbox-0.0.1.dist-info/top_level.txt
gnomad_toolbox-0.0.1.dist-info/RECORD
