Metadata-Version: 2.2
Name: gnomad_toolbox
Version: 0.0.1
Summary: Toolbox to help users process gnomAD release files
Home-page: https://github.com/broadinstitute/gnomad-toolbox
Author: The Genome Aggregation Database
Author-email: gnomad@broadinstitute.org
Project-URL: Documentation, https://broadinstitute.github.io/gnomad-toolbox/
Project-URL: Source Code, https://github.com/broadinstitute/gnomad-toolbox
Project-URL: Issues, https://github.com/broadinstitute/gnomad-toolbox/issues
Project-URL: Change Log, https://github.com/broadinstitute/gnomad-toolbox/releases
Classifier: Topic :: Scientific/Engineering :: Bio-Informatics
Classifier: Intended Audience :: Science/Research
Classifier: License :: OSI Approved :: BSD License
Classifier: Programming Language :: Python :: 3
Classifier: Development Status :: 4 - Beta
Requires-Python: >=3.9
License-File: LICENSE
Requires-Dist: gnomad>=0.8.2
Requires-Dist: hail
Requires-Dist: jupyter
Requires-Dist: jupyter_contrib_nbextensions
Requires-Dist: jupyter_nbextensions_configurator
Requires-Dist: jupyterlab
Requires-Dist: nodejs
Requires-Dist: npm
Requires-Dist: jupyter-server<2.0.0
Dynamic: author
Dynamic: author-email
Dynamic: classifier
Dynamic: description
Dynamic: description-content-type
Dynamic: home-page
Dynamic: project-url
Dynamic: requires-dist
Dynamic: requires-python
Dynamic: summary
